<?xml version="1.0" encoding="UTF-8"?>
<Hotels xmlns:xsi="http://www.w3.org/2001/XMLSchema-instance"
        xsi:noNamespaceSchemaLocation="https://raw.githubusercontent.com/jcoawett/cse445-xml-assignment/main/Hotels.xsd">
  <!-- Hotel Example from Figure 1 -->
  <Hotel Rating="4.2">
    <Name>Westin</Name>
    <Phone>800-937-8461</Phone>
    <Phone>480-968-8885</Phone>
    <Address NearestAirport="Sky Harbor">
      <Number>11</Number>
      <Street>E.7th St</Street>
      <City>Tempe</City>
      <State>AZ</State>
      <Zip>85281</Zip>
    </Address>
  </Hotel>
  
  <!-- Additional 10 Real Hotels in Tempe/Scottsdale, AZ -->
  <Hotel Rating="4.0">
    <Name>Courtyard by Marriott Tempe</Name>
    <Phone>480-769-2000</Phone>
    <Address NearestAirport="Sky Harbor">
      <Number>100</Number>
      <Street>S McClintock Dr</Street>
      <City>Tempe</City>
      <State>AZ</State>
      <Zip>85281</Zip>
    </Address>
  </Hotel>
  
  <Hotel Rating="4.1">
    <Name>Embassy Suites by Hilton Tempe</Name>
    <Phone>480-531-1900</Phone>
    <Address NearestAirport="Sky Harbor">
      <Number>350</Number>
      <Street>E Rio Salado Pkwy</Street>
      <City>Tempe</City>
      <State>AZ</State>
      <Zip>85281</Zip>
    </Address>
  </Hotel>
  
  <Hotel Rating="4.0">
    <Name>Hyatt Place Tempe</Name>
    <Phone>480-959-8000</Phone>
    <Address NearestAirport="Sky Harbor">
      <Number>217</Number>
      <Street>W University Dr</Street>
      <City>Tempe</City>
      <State>AZ</State>
      <Zip>85281</Zip>
    </Address>
  </Hotel>
  
  <Hotel Rating="3.9">
    <Name>DoubleTree by Hilton Hotel Tempe</Name>
    <Phone>480-752-3000</Phone>
    <Address NearestAirport="Sky Harbor">
      <Number>100</Number>
      <Street>W University Dr</Street>
      <City>Tempe</City>
      <State>AZ</State>
      <Zip>85281</Zip>
    </Address>
  </Hotel>
  
  <Hotel Rating="4.7">
    <Name>JW Marriott Scottsdale Camelback Inn Resort &amp; Spa</Name>
    <Phone>480-945-6000</Phone>
    <Address NearestAirport="Sky Harbor">
      <Number>7700</Number>
      <Street>E Camelback Rd</Street>
      <City>Paradise Valley</City>
      <State>AZ</State>
      <Zip>85253</Zip>
    </Address>
  </Hotel>
  
  <Hotel Rating="4.4">
    <Name>The Phoenician, a Luxury Collection Resort, Scottsdale</Name>
    <Phone>480-555-1212</Phone>
    <Address NearestAirport="Sky Harbor">
      <Number>6000</Number>
      <Street>W Camelback Rd</Street>
      <City>Scottsdale</City>
      <State>AZ</State>
      <Zip>85251</Zip>
    </Address>
  </Hotel>
  
  <Hotel Rating="4.0">
    <Name>Omni Scottsdale Resort at McCormick Ranch</Name>
    <Phone>480-555-1213</Phone>
    <Address NearestAirport="Sky Harbor">
      <Number>4949</Number>
      <Street>E Camelback Rd</Street>
      <City>Scottsdale</City>
      <State>AZ</State>
      <Zip>85251</Zip>
    </Address>
  </Hotel>
  
  <Hotel Rating="4.2">
    <Name>Fairmont Scottsdale Princess</Name>
    <Phone>480-555-1214</Phone>
    <Address NearestAirport="Sky Harbor">
      <Number>4949</Number>
      <Street>E McDowell Rd</Street>
      <City>Scottsdale</City>
      <State>AZ</State>
      <Zip>85254</Zip>
    </Address>
  </Hotel>
  
  <Hotel Rating="4.3">
    <Name>Hotel Valley Ho</Name>
    <Phone>480-555-1215</Phone>
    <Address NearestAirport="Sky Harbor">
      <Number>70</Number>
      <Street>N Drinkwater Blvd</Street>
      <City>Scottsdale</City>
      <State>AZ</State>
      <Zip>85251</Zip>
    </Address>
  </Hotel>
  
  <Hotel Rating="4.1">
    <Name>The Scott Hotel</Name>
    <Phone>480-555-1216</Phone>
    <Address NearestAirport="Sky Harbor">
      <Number>401</Number>
      <Street>E Camelback Rd</Street>
      <City>Scottsdale</City>
      <State>AZ</State>
      <Zip>85251</Zip>
    </Address>
  </Hotel>
  
</Hotels>
